Workbook

Sheet API Costs
A1: CMO.ie — API Cost Model
A2: What does each scan actually cost us?
A4: MODEL TOKEN PRICING
A5: Model / Provider | B5: Input (per 1M tokens) | C5: Output (per 1M tokens) | D5: Avg tokens/call | E5: Source
A6: Claude Haiku 4.5 (Anthropic) | B6: 0.8 | C6: 4 | D6: 1200 | E6: anthropic.com/pricing, Apr 2026 — Haiku
A7: GPT-4o (OpenAI) | B7: 2.5 | C7: 10 | D7: 1100 | E7: openai.com/pricing, Apr 2026
A8: Gemini 2.0 Flash (Google) | B8: 0.1 | C8: 0.4 | D8: 1000 | E8: ai.google.dev/pricing, Apr 2026
A9: Perplexity Sonar Pro | B9: 3 | C9: 15 | D9: 1200 | E9: docs.perplexity.ai/pricing, Apr 2026
A10: Claude Haiku (analysis step) | B10: 0.8 | C10: 4 | D10: 800 | E10: Same key — brand detection + JSON extraction
A12: COST PER PROMPT × MODEL CHECK
A13: Step | B13: Tokens (est) | C13: Cost per call | D13: Notes
A14: 1. Query model (simulate response) | B14: ~1,200 tokens out | C14: =ROUND((200*B6/1000000)+(1000*C6/1000000),5) -> 0.00416 | D14: ~200 input + ~1000 output tokens (Claude simulating)
A15: 2. Analyse response (brand detection) | B15: ~800 tokens total | C15: =ROUND((600*B10/1000000)+(200*C10/1000000),5) -> 0.00128 | D15: ~600 input + ~200 output tokens (analysis)
A16: TOTAL per prompt × model check | C16: =C14+C15 -> 0.00544
A18: COST PER DAILY SCAN BY PLAN
A19: Plan | B19: Prompts | C19: Models | D19: Checks per scan | E19: Cost per scan
A20: Trial (Free — 10 checks total) | B20: 1 | C20: 3 | D20: =B20*C20 -> 3 | E20: =D20*$C$16 -> 0.01632
A21: Starter (€29/mo) | B21: 25 | C21: 3 | D21: =B21*C21 -> 75 | E21: =D21*$C$16 -> 0.408
A22: Pro (€79/mo) | B22: 50 | C22: 5 | D22: =B22*C22 -> 250 | E22: =D22*$C$16 -> 1.36
A23: Advanced (€199/mo) | B23: 100 | C23: 5 | D23: =B23*C23 -> 500 | E23: =D23*$C$16 -> 2.72
A25: MONTHLY COST (30 daily scans)
A26: Plan | B26: Daily cost | C26: Monthly cost (30d) | D26: Monthly revenue | E26: Gross margin
A27: Trial | B27: =E20 -> 0.01632 | C27: =B27*30 -> 0.4896 | D27: 0 | E27: N/A — trial
A28: Starter (€29/mo) | B28: =E21 -> 0.408 | C28: =B28*30 -> 12.24 | D28: 29 | E28: =(D28-C28)/D28 -> 0.57793103
A29: Pro (€79/mo) | B29: =E22 -> 1.36 | C29: =B29*30 -> 40.8 | D29: 79 | E29: =(D29-C29)/D29 -> 0.4835443
A30: Advanced (€199/mo) | B30: =E23 -> 2.72 | C30: =B30*30 -> 81.6 | D30: 199 | E30: =(D30-C30)/D30 -> 0.58994975

Sheet Revenue Model
A1: CMO.ie — 12 Month Revenue Projection
A2: Flat monthly subscription model — all API costs included
A4: ASSUMPTIONS | B4: Month 1 | C4: Month 2 | D4: Month 3 | E4: Month 4 | F4: Month 5 | G4: Month 6 | H4: Month 7 | I4: Month 8 | J4: Month 9 | K4: Month 10 | L4: Month 11 | M4: Month 12
A5: New trial signups / month | B5: 20 | C5: =ROUND(B5*1.15,0) -> 23 | D5: =ROUND(C5*1.15,0) -> 26 | E5: =ROUND(D5*1.15,0) -> 30 | F5: =ROUND(E5*1.15,0) -> 35 | G5: =ROUND(F5*1.15,0) -> 40 | H5: =ROUND(G5*1.15,0) -> 46 | I5: =ROUND(H5*1.15,0) -> 53 | J5: =ROUND(I5*1.15,0) -> 61 | ... M5: =ROUND(L5*1.15,0) -> 93
A6: Trial → Starter conversion % | B6: 0.12 | C6: 0.12 | D6: 0.12 | E6: 0.12 | F6: 0.12 | G6: 0.12 | H6: 0.12 | I6: 0.12 | J6: 0.12 | K6: 0.12 | L6: 0.12 | M6: 0.12
A7: Starter → Pro upgrade % (monthly) | B7: 0.08 | C7: 0.08 | D7: 0.08 | E7: 0.08 | F7: 0.08 | G7: 0.08 | H7: 0.08 | I7: 0.08 | J7: 0.08 | K7: 0.08 | L7: 0.08 | M7: 0.08
A8: Pro → Advanced upgrade % (monthly) | B8: 0.03 | C8: 0.03 | D8: 0.03 | E8: 0.03 | F8: 0.03 | G8: 0.03 | H8: 0.03 | I8: 0.03 | J8: 0.03 | K8: 0.03 | L8: 0.03 | M8: 0.03
A9: Monthly churn % (all paid) | B9: 0.05 | C9: 0.05 | D9: 0.05 | E9: 0.05 | F9: 0.05 | G9: 0.05 | H9: 0.05 | I9: 0.05 | J9: 0.05 | K9: 0.05 | L9: 0.05 | M9: 0.05
A11: ACTIVE CUSTOMERS
A12: Trial users (active) | B12: =B5 -> 20 | C12: =ROUND(C5 + B12*0.5*(1-C6), 0) -> 32 | D12: =ROUND(D5 + C12*0.5*(1-D6), 0) -> 40 | E12: =ROUND(E5 + D12*0.5*(1-E6), 0) -> 48 | F12: =ROUND(F5 + E12*0.5*(1-F6), 0) -> 56 | G12: =ROUND(G5 + F12*0.5*(1-G6), 0) -> 65 | H12: =ROUND(H5 + G12*0.5*(1-H6), 0) -> 75 | I12: =ROUND(I5 + H12*0.5*(1-I6), 0) -> 86 | J12: =ROUND(J5 + I12*0.5*(1-J6), 0) -> 99 | ... M12: =ROUND(M5 + L12*0.5*(1-M6), 0) -> 151
A13: Starter customers | B13: =ROUND(B12*B6, 0) -> 2 | C13: =MAX(0, ROUND(B13*(1-C9-C7) + C12*C6, 0)) -> 6 | D13: =MAX(0, ROUND(C13*(1-D9-D7) + D12*D6, 0)) -> 10 | E13: =MAX(0, ROUND(D13*(1-E9-E7) + E12*E6, 0)) -> 14 | F13: =MAX(0, ROUND(E13*(1-F9-F7) + F12*F6, 0)) -> 19 | G13: =MAX(0, ROUND(F13*(1-G9-G7) + G12*G6, 0)) -> 24 | H13: =MAX(0, ROUND(G13*(1-H9-H7) + H12*H6, 0)) -> 30 | I13: =MAX(0, ROUND(H13*(1-I9-I7) + I12*I6, 0)) -> 36 | J13: =MAX(0, ROUND(I13*(1-J9-J7) + J12*J6, 0)) -> 43 | ... M13: =MAX(0, ROUND(L13*(1-M9-M7) + M12*M6, 0)) -> 70
A14: Pro customers | B14: =ROUND(B13*B7, 0) -> 0 | C14: =MAX(0, ROUND(B14*(1-C9-C8) + C13*C7, 0)) -> 0 | D14: =MAX(0, ROUND(C14*(1-D9-D8) + D13*D7, 0)) -> 1 | E14: =MAX(0, ROUND(D14*(1-E9-E8) + E13*E7, 0)) -> 2 | F14: =MAX(0, ROUND(E14*(1-F9-F8) + F13*F7, 0)) -> 3 | G14: =MAX(0, ROUND(F14*(1-G9-G8) + G13*G7, 0)) -> 5 | H14: =MAX(0, ROUND(G14*(1-H9-H8) + H13*H7, 0)) -> 7 | I14: =MAX(0, ROUND(H14*(1-I9-I8) + I13*I7, 0)) -> 9 | J14: =MAX(0, ROUND(I14*(1-J9-J8) + J13*J7, 0)) -> 12 | ... M14: =MAX(0, ROUND(L14*(1-M9-M8) + M13*M7, 0)) -> 23
A15: Advanced customers | B15: =ROUND(B14*B8, 0) -> 0 | C15: =MAX(0, ROUND(B15*(1-C9) + C14*C8, 0)) -> 0 | D15: =MAX(0, ROUND(C15*(1-D9) + D14*D8, 0)) -> 0 | E15: =MAX(0, ROUND(D15*(1-E9) + E14*E8, 0)) -> 0 | F15: =MAX(0, ROUND(E15*(1-F9) + F14*F8, 0)) -> 0 | G15: =MAX(0, ROUND(F15*(1-G9) + G14*G8, 0)) -> 0 | H15: =MAX(0, ROUND(G15*(1-H9) + H14*H8, 0)) -> 0 | I15: =MAX(0, ROUND(H15*(1-I9) + I14*I8, 0)) -> 0 | J15: =MAX(0, ROUND(I15*(1-J9) + J14*J8, 0)) -> 0 | ... M15: =MAX(0, ROUND(L15*(1-M9) + M14*M8, 0)) -> 2
A16: Total paying customers | B16: =B13+B14+B15 -> 2 | C16: =C13+C14+C15 -> 6 | D16: =D13+D14+D15 -> 11 | E16: =E13+E14+E15 -> 16 | F16: =F13+F14+F15 -> 22 | G16: =G13+G14+G15 -> 29 | H16: =H13+H14+H15 -> 37 | I16: =I13+I14+I15 -> 45 | ... M16: =M13+M14+M15 -> 95
A18: MONTHLY REVENUE
A19: Starter revenue (€29/mo) | B19: =B13*29 -> 58 | C19: =C13*29 -> 174 | D19: =D13*29 -> 290 | E19: =E13*29 -> 406 | F19: =F13*29 -> 551 | G19: =G13*29 -> 696 | H19: =H13*29 -> 870 | I19: =I13*29 -> 1044 | ... M19: =M13*29 -> 2030
A20: Pro revenue (€79/mo) | B20: =B14*79 -> 0 | C20: =C14*79 -> 0 | D20: =D14*79 -> 79 | E20: =E14*79 -> 158 | F20: =F14*79 -> 237 | G20: =G14*79 -> 395 | H20: =H14*79 -> 553 | I20: =I14*79 -> 711 | ... M20: =M14*79 -> 1817
A21: Advanced revenue (€199/mo) | B21: =B15*199 -> 0 | C21: =C15*199 -> 0 | D21: =D15*199 -> 0 | E21: =E15*199 -> 0 | F21: =F15*199 -> 0 | G21: =G15*199 -> 0 | H21: =H15*199 -> 0 | I21: =I15*199 -> 0 | ... M21: =M15*199 -> 398
A22: TOTAL REVENUE | B22: =B19+B20+B21 -> 58 | C22: =C19+C20+C21 -> 174 | D22: =D19+D20+D21 -> 369 | E22: =E19+E20+E21 -> 564 | F22: =F19+F20+F21 -> 788 | G22: =G19+G20+G21 -> 1091 | H22: =H19+H20+H21 -> 1423 | I22: =I19+I20+I21 -> 1755 | ... M22: =M19+M20+M21 -> 4245
A24: MONTHLY API COSTS
A25: Trial API cost (10 checks total/user) | B25: =B12 * 10 * 'API Costs'!$C$16 -> 1.088 | C25: =C12 * 10 * 'API Costs'!$C$16 -> 1.7408 | D25: =D12 * 10 * 'API Costs'!$C$16 -> 2.176 | E25: =E12 * 10 * 'API Costs'!$C$16 -> 2.6112 | F25: =F12 * 10 * 'API Costs'!$C$16 -> 3.0464 | G25: =G12 * 10 * 'API Costs'!$C$16 -> 3.536 | H25: =H12 * 10 * 'API Costs'!$C$16 -> 4.08 | I25: =I12 * 10 * 'API Costs'!$C$16 -> 4.6784 | ... M25: =M12 * 10 * 'API Costs'!$C$16 -> 8.2144
A26: Starter API cost | B26: =B13 * 75 * 'API Costs'!$C$16 * 30 -> 24.48 | C26: =C13 * 75 * 'API Costs'!$C$16 * 30 -> 73.44 | D26: =D13 * 75 * 'API Costs'!$C$16 * 30 -> 122.4 | E26: =E13 * 75 * 'API Costs'!$C$16 * 30 -> 171.36 | F26: =F13 * 75 * 'API Costs'!$C$16 * 30 -> 232.56 | G26: =G13 * 75 * 'API Costs'!$C$16 * 30 -> 293.76 | H26: =H13 * 75 * 'API Costs'!$C$16 * 30 -> 367.2 | I26: =I13 * 75 * 'API Costs'!$C$16 * 30 -> 440.64 | ... M26: =M13 * 75 * 'API Costs'!$C$16 * 30 -> 856.8
A27: Pro API cost | B27: =B14 * 250 * 'API Costs'!$C$16 * 30 -> 0 | C27: =C14 * 250 * 'API Costs'!$C$16 * 30 -> 0 | D27: =D14 * 250 * 'API Costs'!$C$16 * 30 -> 40.8 | E27: =E14 * 250 * 'API Costs'!$C$16 * 30 -> 81.6 | F27: =F14 * 250 * 'API Costs'!$C$16 * 30 -> 122.4 | G27: =G14 * 250 * 'API Costs'!$C$16 * 30 -> 204 | H27: =H14 * 250 * 'API Costs'!$C$16 * 30 -> 285.6 | I27: =I14 * 250 * 'API Costs'!$C$16 * 30 -> 367.2 | ... M27: =M14 * 250 * 'API Costs'!$C$16 * 30 -> 938.4
A28: Advanced API cost | B28: =B15 * 500 * 'API Costs'!$C$16 * 30 -> 0 | C28: =C15 * 500 * 'API Costs'!$C$16 * 30 -> 0 | D28: =D15 * 500 * 'API Costs'!$C$16 * 30 -> 0 | E28: =E15 * 500 * 'API Costs'!$C$16 * 30 -> 0 | F28: =F15 * 500 * 'API Costs'!$C$16 * 30 -> 0 | G28: =G15 * 500 * 'API Costs'!$C$16 * 30 -> 0 | H28: =H15 * 500 * 'API Costs'!$C$16 * 30 -> 0 | I28: =I15 * 500 * 'API Costs'!$C$16 * 30 -> 0 | ... M28: =M15 * 500 * 'API Costs'!$C$16 * 30 -> 163.2
A29: TOTAL API COST | B29: =B25+B26+B27+B28 -> 25.568 | C29: =C25+C26+C27+C28 -> 75.1808 | D29: =D25+D26+D27+D28 -> 165.376 | E29: =E25+E26+E27+E28 -> 255.5712 | F29: =F25+F26+F27+F28 -> 358.0064 | G29: =G25+G26+G27+G28 -> 501.296 | H29: =H25+H26+H27+H28 -> 656.88 | I29: =I25+I26+I27+I28 -> 812.5184 | ... M29: =M25+M26+M27+M28 -> 1966.6144
A31: P&L SUMMARY
A32: Total Revenue | B32: =B22 -> 58 | C32: =C22 -> 174 | D32: =D22 -> 369 | E32: =E22 -> 564 | F32: =F22 -> 788 | G32: =G22 -> 1091 | H32: =H22 -> 1423 | I32: =I22 -> 1755 | ... M32: =M22 -> 4245
A33: Total API Cost | B33: =B29 -> 25.568 | C33: =C29 -> 75.1808 | D33: =D29 -> 165.376 | E33: =E29 -> 255.5712 | F33: =F29 -> 358.0064 | G33: =G29 -> 501.296 | H33: =H29 -> 656.88 | I33: =I29 -> 812.5184 | ... M33: =M29 -> 1966.6144
A34: GROSS PROFIT | B34: =B32-B33 -> 32.432 | C34: =C32-C33 -> 98.8192 | D34: =D32-D33 -> 203.624 | E34: =E32-E33 -> 308.4288 | F34: =F32-F33 -> 429.9936 | G34: =G32-G33 -> 589.704 | H34: =H32-H33 -> 766.12 | I34: =I32-I33 -> 942.4816 | ... M34: =M32-M33 -> 2278.3856
A35: Gross Margin % | B35: =IF(B32>0,B34/B32,0) -> 0.55917241 | C35: =IF(C32>0,C34/C32,0) -> 0.56792644 | D35: =IF(D32>0,D34/D32,0) -> 0.55182656 | E35: =IF(E32>0,E34/E32,0) -> 0.54685957 | F35: =IF(F32>0,F34/F32,0) -> 0.54567716 | G35: =IF(G32>0,G34/G32,0) -> 0.54051696 | H35: =IF(H32>0,H34/H32,0) -> 0.5383837 | I35: =IF(I32>0,I34/I32,0) -> 0.53702655 | ... M35: =IF(M32>0,M34/M32,0) -> 0.53672217
A37: CUMULATIVE | B37: =B34 -> 32.432 | C37: =B37+C34 -> 131.2512 | D37: =C37+D34 -> 334.8752 | E37: =D37+E34 -> 643.304 | F37: =E37+F34 -> 1073.2976 | G37: =F37+G34 -> 1663.0016 | H37: =G37+H34 -> 2429.1216 | I37: =H37+I34 -> 3371.6032 | J37: =I37+J34 -> 4545.2976 | ... M37: =L37+M34 -> 10086.915

Sheet Plan Comparison
A1: CMO.ie — Plan Comparison & Pricing Rationale
A3: Feature | B3: Trial (Free) | C3: Starter (€29) | D3: Pro (€79) | E3: Advanced (€199)
A4: Monthly price | B4: €0 | C4: €29 | D4: €79 | E4: €199
A5: Projects | B5: 1 | C5: 1 | D5: 3 | E5: Unlimited
A6: Prompts per project | B6: 1 | C6: 25 | D6: 50 | E6: 100
A7: AI Models | B7: 3 | C7: 3 | D7: 5 | E7: 5
A8: Daily scans | B8: 10 checks total | C8: Daily | D8: Daily | E8: Daily
A9: Checks per scan | B9: 3 | C9: 75 | D9: 250 | E9: 500
A10: Action plan tier | B10: Gap analysis | C10: Gap analysis | D10: Strategy + actions | E10: Full + briefs
A11: Brief credits / month | B11: 0 | C11: 5 | D11: 20 | E11: Unlimited
A12: Team members | B12: 1 | C12: 1 | D12: 3 | E12: Unlimited
A14: API cost per scan | B14: =3*'API Costs'!$C$16 -> 0.01632 | C14: =75*'API Costs'!$C$16 -> 0.408 | D14: =250*'API Costs'!$C$16 -> 1.36 | E14: =500*'API Costs'!$C$16 -> 2.72
A15: Monthly API cost (or total for trial) | B15: =10*'API Costs'!$C$16 -> 0.0544 | C15: =75*'API Costs'!$C$16*30 -> 12.24 | D15: =250*'API Costs'!$C$16*30 -> 40.8 | E15: =500*'API Costs'!$C$16*30 -> 81.6
A16: Monthly revenue | B16: 0 | C16: 29 | D16: 79 | E16: 199
A17: Gross profit per customer | B17: =B16-B15 -> -0.0544 | C17: =C16-C15 -> 16.76 | D17: =D16-D15 -> 38.2 | E17: =E16-E15 -> 117.4
A18: Gross margin | B18: N/A | C18: =IF(C16>0,C17/C16,0) -> 0.57793103 | D18: =IF(D16>0,D17/D16,0) -> 0.4835443 | E18: =IF(E16>0,E17/E16,0) -> 0.58994975
A21: KEY INSIGHT
A22: With Haiku, all API costs run through Anthropic at ~€0.005/check (vs €0.02 with Sonnet).
A23: This makes every paid plan profitable. Trial costs ~€0.05 per user (10 checks × €0.005).
A25: COST REDUCTION STRATEGIES:
A26: 1. Use Claude Haiku for the simulation step (10x cheaper, ~€0.002/check)
A27: 2. Cache common prompt responses (same prompt rarely changes day-to-day)
A28: 3. Use batch API for non-urgent daily scans (50% discount)
A29: 4. Eventually integrate direct model APIs (OpenAI, Google) for more authentic results AND lower costs
